{"rows":[{"columns":[{"size":"col-md-12","containers":[{"genType":"container","proprieties":{"tag":"sectionheader_1","type":"sectionheader","text":"<p>Informa&ccedil;&otilde;es Gerais&nbsp;</p>\n","maxlength":4000,"font-size":"h4"},"fields":[],"style":{"id":"","class":"","inline":""},"options":{"autoTag":false},"id":"sectionheader1701596961832","xsl":{"useDefault":true}},{"genType":"container","proprieties":{"title":"Informações do ativo","tag":"form_1","type":"form"},"fields":[{"properties":{"_id":"text_e37e_9c0a","label":"Nome","tag":"nome","name":"p_nome","type":"text","maxlength":250,"required":true,"change":false,"readonly":false,"disabled":false,"disablehtml":true,"placeholder":"","inputmask":"","size":"6"},"style":{"id":"","class":"","inline":""},"options":{"autoTag":false,"rules":[]},"xsl":{"useDefault":true,"template":false},"validation":[{"annotation":"@NotNull","value":"","integer":"","numeric":"","min":"","max":"","message":""}]},{"properties":{"_id":"text_1df3_b67f","label":"Código","tag":"codigo","name":"p_codigo","type":"text","maxlength":250,"required":false,"change":false,"readonly":false,"disabled":false,"disablehtml":true,"placeholder":"","inputmask":"","size":"6"},"style":{"id":"","class":"","inline":""},"options":{"autoTag":false,"rules":[]},"xsl":{"useDefault":true,"template":false},"validation":[]},{"properties":{"_id":"select_8eaf_f3b6","label":"Estado","tag":"estado","name":"p_estado","type":"select","placeholder":"","multiple":false,"tags":false,"load_service_data":false,"domain_value":[],"domain":"","maxlength":250,"required":false,"change":false,"disabled":false,"size":"6","java-type":""},"style":{"id":"","class":"","inline":""},"options":{"autoTag":false,"rules":[]},"xsl":{"useDefault":true,"template":false},"validation":[]},{"properties":{"_id":"select_4170_238e","label":"Categoria","tag":"categoria","name":"p_categoria","type":"select","placeholder":"","multiple":false,"tags":false,"load_service_data":false,"domain_value":[],"domain":"","maxlength":250,"required":false,"change":false,"disabled":false,"size":"6","java-type":""},"style":{"id":"","class":"","inline":""},"options":{"autoTag":false,"rules":[]},"xsl":{"useDefault":true,"template":false},"validation":[]},{"properties":{"_id":"number_e74b_8789","label":"Garantia","tag":"garantia","name":"p_garantia","type":"number","min":"","max":"","calculation":false,"mathcal":"","numberformat":"","maxlength":250,"required":false,"change":false,"readonly":false,"disabled":false,"placeholder":"","size":"6","java-type":""},"style":{"id":"","class":"","inline":""},"options":{"autoTag":false,"rules":[]},"xsl":{"useDefault":true,"template":false},"validation":[]}],"style":{"id":"","class":"","inline":""},"options":{"autoTag":true},"id":"form1701596255891","xsl":{"useDefault":true}},{"genType":"container","proprieties":{"tag":"sectionheader_2","type":"sectionheader","text":"<p>Informa&ccedil;&otilde;es de compra/venda</p>\n","maxlength":4000,"font-size":"h4"},"fields":[],"style":{"id":"","class":"","inline":""},"options":{"autoTag":false},"id":"sectionheader1701597016957","xsl":{"useDefault":true}},{"genType":"container","proprieties":{"title":"Informações de compra e venda","tag":"buyandsell","type":"form"},"fields":[{"properties":{"_id":"text_34c5_b3e8","label":"Valor da compra","tag":"valor_da_compra","name":"p_valor_da_compra","type":"text","maxlength":250,"required":false,"change":false,"readonly":false,"disabled":false,"disablehtml":true,"placeholder":"","inputmask":"","size":"6"},"style":{"id":"","class":"","inline":""},"options":{"autoTag":false,"rules":[]},"xsl":{"useDefault":true,"template":false},"validation":[]},{"properties":{"_id":"text_ee7d_efe4","label":"Valor da venda ","tag":"valor_da_venda","name":"p_valor_da_venda","type":"text","maxlength":250,"required":false,"change":false,"readonly":false,"disabled":false,"disablehtml":true,"placeholder":"","inputmask":"","size":"6"},"style":{"id":"","class":"","inline":""},"options":{"autoTag":false,"rules":[]},"xsl":{"useDefault":true,"template":false},"validation":[]},{"properties":{"_id":"date_8930_f90b","label":"Data da compra ","tag":"data_da_compra","name":"p_data_da_compra","type":"date","format":"d-m-Y","enableTime":false,"range":false,"disableWeekends":false,"disabledBeforetoday":false,"daysoff":false,"maxlength":250,"required":false,"change":false,"readonly":false,"disabled":false,"placeholder":"","size":"6"},"style":{"id":"","class":"","inline":""},"options":{"autoTag":false,"rules":[]},"xsl":{"useDefault":true,"template":false},"validation":[]},{"properties":{"_id":"date_0165_693c","label":"Data da venda","tag":"data_da_venda","name":"p_data_da_venda","type":"date","format":"d-m-Y","enableTime":false,"range":false,"disableWeekends":false,"disabledBeforetoday":false,"daysoff":false,"maxlength":250,"required":false,"change":false,"readonly":false,"disabled":false,"placeholder":"","size":"6"},"style":{"id":"","class":"","inline":""},"options":{"autoTag":false,"rules":[]},"xsl":{"useDefault":true,"template":false},"validation":[]}],"style":{"id":"","class":"","inline":""},"options":{"autoTag":false},"id":"form1701597054112","xsl":{"useDefault":true}}]}],"propreties":{"class":""}},{"columns":[{"size":"col-md-12","containers":[{"genType":"container","proprieties":{"title":"Atribuição","tag":"atribuicao","type":"form"},"fields":[{"properties":{"_id":"text_b93b_f138","label":"Departamento","tag":"departamento","name":"p_departamento","type":"text","maxlength":250,"required":false,"change":false,"readonly":false,"disabled":false,"disablehtml":true,"placeholder":"","inputmask":"","size":"3"},"style":{"id":"","class":"","inline":""},"options":{"autoTag":false,"rules":[]},"xsl":{"useDefault":true,"template":false},"validation":[]},{"properties":{"_id":"text_33c3_b8be","label":"Funcionário ","tag":"funcionario","name":"p_funcionario","type":"text","maxlength":250,"required":false,"change":false,"readonly":false,"disabled":false,"disablehtml":true,"placeholder":"","inputmask":"","size":"6"},"style":{"id":"","class":"","inline":""},"options":{"autoTag":false,"rules":[]},"xsl":{"useDefault":true,"template":false},"validation":[]}],"style":{"id":"","class":"","inline":""},"options":{"autoTag":false},"id":"form1701597473338","xsl":{"useDefault":true}}]}],"propreties":{"class":""}}],"plsql":{"instance":"","table":"","package":"Registro de Ativos","html":"Registro de Ativos","gentype":"java","replace":false,"label":false,"biztalk":false,"process":false,"subversionpath":""},"css":"","js":"","files":{"css":[],"js":[],"xsl":[]},"service":{"value":{"code":"","desc":"","proc":"","connectionsReq":[],"fieldsReq":[],"connectionsRes":[],"fieldsRes":[]}},"version":"2.4","blocklyData":"<xml><block type=\"controller\" id=\"controller\" x=\"388\" y=\"13\"></block></xml>"}
